odoo/addons/web_widget_float_formula/README.rst
odoo/addons/web_widget_float_formula/__init__.py
odoo/addons/web_widget_float_formula/__manifest__.py
odoo/addons/web_widget_float_formula/i18n/ca.po
odoo/addons/web_widget_float_formula/i18n/es.po
odoo/addons/web_widget_float_formula/i18n/pt_BR.po
odoo/addons/web_widget_float_formula/i18n/web_widget_float_formula.pot
odoo/addons/web_widget_float_formula/readme/CONTRIBUTORS.rst
odoo/addons/web_widget_float_formula/readme/DESCRIPTION.rst
odoo/addons/web_widget_float_formula/readme/ROADMAP.rst
odoo/addons/web_widget_float_formula/static/description/icon.png
odoo/addons/web_widget_float_formula/static/description/index.html
odoo/addons/web_widget_float_formula/static/src/js/web_widget_float_formula.js
odoo/addons/web_widget_float_formula/static/tests/js/test_web_widget_float_formula.js
odoo/addons/web_widget_float_formula/templates/assets.xml
odoo12_addon_web_widget_float_formula-12.0.1.0.1.dist-info/METADATA
odoo12_addon_web_widget_float_formula-12.0.1.0.1.dist-info/WHEEL
odoo12_addon_web_widget_float_formula-12.0.1.0.1.dist-info/top_level.txt
odoo12_addon_web_widget_float_formula-12.0.1.0.1.dist-info/RECORD
